zonefilegen/__init__.py
zonefilegen/cli.py
zonefilegen/core.py
zonefilegen/generation.py
zonefilegen/parsing.py
zonefilegen-0.2.0.dist-info/LICENSE
zonefilegen-0.2.0.dist-info/METADATA
zonefilegen-0.2.0.dist-info/WHEEL
zonefilegen-0.2.0.dist-info/entry_points.txt
zonefilegen-0.2.0.dist-info/top_level.txt
zonefilegen-0.2.0.dist-info/RECORD
