Metadata-Version: 2.1
Name: zonefilegen
Version: 0.2.0
Summary: A library and tool to generate sychronized forward and reverse DNS zone files.
Author-email: Karl Linderhed <zonefilegen@karlinde.se>
License: MIT License
Project-URL: repository, https://github.com/karlinde/zonefilegen
Project-URL: Bug Tracker, https://github.com/karlinde/zonefilegen/issues
Classifier: Programming Language :: Python :: 3
Classifier: License :: OSI Approved :: MIT License
Classifier: Operating System :: OS Independent
Requires-Python: >=3.8
License-File: LICENSE
Requires-Dist: toml
